{
  "_comment" : "Created with OWL2VOWL (version 0.3.5), http://vowl.visualdataweb.org",
  "header" : {
    "languages" : [ "undefined" ],
    "baseIris" : [ "http://www.loa.istc.cnr.it/ontologies/DOLCE-Lite.owl", "http://www.w3.org/2000/01/rdf-schema", "https://schema.org", "http://www.w3.org/2001/XMLSchema", "https://github.com/dice-group/rtaso/main/rtaso.owl", "http://xmlns.com/foaf/0.1" ],
    "iri" : "https://github.com/dice-group/rtaso/main/rtaso.owl#RoadTraficAccidentSeverityOntology",
    "author" : [ "Hizkiel Mitiku Alemayehu", "Axel-Cyrille Ngonga Ngomo", "Tibebe Beshah" ],
    "description" : {
      "undefined" : "\n        The Car Accident Severity Ontology (rtaso) provides a comprehensive and reusable semantic model for representing car accident severity and its associated factors. \n        It leverages established ontologies and vocabularies to ensure interoperability with existing datasets and tools, while introducing domain-specific concepts tailored to accident analysis. \n        By formalizing relationships between accident entities, rtaso enables advanced querying, reasoning, and knowledge extraction, supporting applications in accident investigation, risk assessment, and policy development.\n\n        This document outlines the structure, design principles, and potential use cases of rtaso, demonstrating its value as a resource for researchers and practitioners in the field of transportation safety.\n    "
    },
    "labels" : {
      "undefined" : "Car Accident Severity Ontology (rtaso)"
    },
    "comments" : {
      "undefined" : "An ontology for modeling car accident severity and related factors. Reuses existing vocabularies where applicable."
    },
    "other" : {
      "license" : [ {
        "identifier" : "license",
        "language" : "undefined",
        "value" : "http://creativecommons.org/licenses/by/4.0/",
        "type" : "iri"
      } ],
      "creator" : [ {
        "identifier" : "creator",
        "language" : "undefined",
        "value" : "Tibebe Beshah",
        "type" : "label"
      }, {
        "identifier" : "creator",
        "language" : "undefined",
        "value" : "Hizkiel Mitiku Alemayehu",
        "type" : "label"
      }, {
        "identifier" : "creator",
        "language" : "undefined",
        "value" : "Axel-Cyrille Ngonga Ngomo",
        "type" : "label"
      } ],
      "abstract" : [ {
        "identifier" : "abstract",
        "language" : "undefined",
        "value" : "\n        The Car Accident Severity Ontology (rtaso) is a formalized knowledge representation framework designed to model factors influencing the severity of car accidents.\n    ",
        "type" : "label"
      } ],
      "issued" : [ {
        "identifier" : "issued",
        "language" : "undefined",
        "value" : "2024-01-28",
        "type" : "label"
      } ]
    }
  },
  "namespace" : [ ],
  "class" : [ {
    "id" : "6",
    "type" : "owl:Class"
  }, {
    "id" : "10",
    "type" : "rdfs:Datatype"
  }, {
    "id" : "9",
    "type" : "rdfs:Datatype"
  }, {
    "id" : "11",
    "type" : "rdfs:Datatype"
  }, {
    "id" : "12",
    "type" : "rdfs:Datatype"
  }, {
    "id" : "13",
    "type" : "rdfs:Datatype"
  }, {
    "id" : "14",
    "type" : "rdfs:Datatype"
  }, {
    "id" : "15",
    "type" : "rdfs:Datatype"
  }, {
    "id" : "16",
    "type" : "rdfs:Datatype"
  }, {
    "id" : "19",
    "type" : "owl:Class"
  }, {
    "id" : "5",
    "type" : "owl:Class"
  }, {
    "id" : "23",
    "type" : "owl:Class"
  }, {
    "id" : "24",
    "type" : "rdfs:Datatype"
  }, {
    "id" : "2",
    "type" : "rdfs:Datatype"
  }, {
    "id" : "27",
    "type" : "owl:Class"
  }, {
    "id" : "7",
    "type" : "owl:Class"
  }, {
    "id" : "18",
    "type" : "owl:Class"
  }, {
    "id" : "4",
    "type" : "owl:Class"
  }, {
    "id" : "1",
    "type" : "owl:Class"
  }, {
    "id" : "22",
    "type" : "rdfs:Datatype"
  }, {
    "id" : "31",
    "type" : "owl:Class"
  }, {
    "id" : "39",
    "type" : "rdfs:Datatype"
  }, {
    "id" : "41",
    "type" : "rdfs:Datatype"
  } ],
  "classAttribute" : [ {
    "iri" : "https://github.com/dice-group/rtaso/main/rtaso.owl#Road",
    "baseIri" : "https://github.com/dice-group/rtaso/main/rtaso.owl",
    "instances" : 0,
    "label" : {
      "IRI-based" : "Road",
      "undefined" : "Road"
    },
    "comment" : {
      "undefined" : "Represents the road conditions during an accident."
    },
    "attributes" : [ "external" ],
    "id" : "6",
    "superClasses" : [ "7" ]
  }, {
    "iri" : "http://www.w3.org/2001/XMLSchema#string",
    "baseIri" : "http://www.w3.org/2001/XMLSchema",
    "id" : "10",
    "label" : {
      "IRI-based" : "string"
    }
  }, {
    "iri" : "http://www.w3.org/2001/XMLSchema#integer",
    "baseIri" : "http://www.w3.org/2001/XMLSchema",
    "id" : "9",
    "label" : {
      "IRI-based" : "integer"
    }
  }, {
    "iri" : "http://www.w3.org/2001/XMLSchema#string",
    "baseIri" : "http://www.w3.org/2001/XMLSchema",
    "id" : "11",
    "label" : {
      "IRI-based" : "string"
    }
  }, {
    "iri" : "http://www.w3.org/2001/XMLSchema#string",
    "baseIri" : "http://www.w3.org/2001/XMLSchema",
    "id" : "12",
    "label" : {
      "IRI-based" : "string"
    }
  }, {
    "iri" : "http://www.w3.org/2001/XMLSchema#string",
    "baseIri" : "http://www.w3.org/2001/XMLSchema",
    "id" : "13",
    "label" : {
      "IRI-based" : "string"
    }
  }, {
    "iri" : "http://www.w3.org/2001/XMLSchema#string",
    "baseIri" : "http://www.w3.org/2001/XMLSchema",
    "id" : "14",
    "label" : {
      "IRI-based" : "string"
    }
  }, {
    "iri" : "http://www.w3.org/2001/XMLSchema#integer",
    "baseIri" : "http://www.w3.org/2001/XMLSchema",
    "id" : "15",
    "label" : {
      "IRI-based" : "integer"
    }
  }, {
    "iri" : "http://www.w3.org/2001/XMLSchema#string",
    "baseIri" : "http://www.w3.org/2001/XMLSchema",
    "id" : "16",
    "label" : {
      "IRI-based" : "string"
    }
  }, {
    "iri" : "https://schema.org/Vehicle",
    "baseIri" : "https://schema.org",
    "instances" : 0,
    "label" : {
      "IRI-based" : "Vehicle"
    },
    "subClasses" : [ "5" ],
    "attributes" : [ "external" ],
    "id" : "19"
  }, {
    "iri" : "https://github.com/dice-group/rtaso/main/rtaso.owl#Vehicle",
    "baseIri" : "https://github.com/dice-group/rtaso/main/rtaso.owl",
    "instances" : 0,
    "label" : {
      "IRI-based" : "Vehicle",
      "undefined" : "Vehicle"
    },
    "comment" : {
      "undefined" : "Represents the vehicle involved in an accident."
    },
    "attributes" : [ "external" ],
    "id" : "5",
    "superClasses" : [ "19" ]
  }, {
    "iri" : "https://github.com/dice-group/rtaso/main/rtaso.owl#Environment",
    "baseIri" : "https://github.com/dice-group/rtaso/main/rtaso.owl",
    "instances" : 0,
    "label" : {
      "IRI-based" : "Environment",
      "undefined" : "Environment"
    },
    "comment" : {
      "undefined" : "Represents the environmental conditions during an accident."
    },
    "attributes" : [ "external" ],
    "id" : "23",
    "superClasses" : [ "7" ]
  }, {
    "iri" : "http://www.w3.org/2001/XMLSchema#integer",
    "baseIri" : "http://www.w3.org/2001/XMLSchema",
    "id" : "24",
    "label" : {
      "IRI-based" : "integer"
    }
  }, {
    "iri" : "http://www.w3.org/2001/XMLSchema#string",
    "baseIri" : "http://www.w3.org/2001/XMLSchema",
    "id" : "2",
    "label" : {
      "IRI-based" : "string"
    }
  }, {
    "iri" : "http://www.loa.istc.cnr.it/ontologies/DOLCE-Lite.owl#Event",
    "baseIri" : "http://www.loa.istc.cnr.it/ontologies/DOLCE-Lite.owl",
    "instances" : 0,
    "label" : {
      "IRI-based" : "Event"
    },
    "subClasses" : [ "1" ],
    "attributes" : [ "external" ],
    "id" : "27"
  }, {
    "iri" : "https://schema.org/Place",
    "baseIri" : "https://schema.org",
    "instances" : 0,
    "label" : {
      "IRI-based" : "Place"
    },
    "subClasses" : [ "6", "23" ],
    "attributes" : [ "external" ],
    "id" : "7"
  }, {
    "iri" : "https://github.com/dice-group/rtaso/main/rtaso.owl#Casualty",
    "baseIri" : "https://github.com/dice-group/rtaso/main/rtaso.owl",
    "instances" : 0,
    "label" : {
      "IRI-based" : "Casualty",
      "undefined" : "Casualty"
    },
    "comment" : {
      "undefined" : "Represents the victims or casualties of an accident."
    },
    "attributes" : [ "external" ],
    "id" : "18",
    "superClasses" : [ "31" ]
  }, {
    "iri" : "https://github.com/dice-group/rtaso/main/rtaso.owl#Driver",
    "baseIri" : "https://github.com/dice-group/rtaso/main/rtaso.owl",
    "instances" : 0,
    "label" : {
      "IRI-based" : "Driver",
      "undefined" : "Driver"
    },
    "comment" : {
      "undefined" : "Represents the driver involved in an accident."
    },
    "attributes" : [ "external" ],
    "id" : "4",
    "superClasses" : [ "31" ]
  }, {
    "iri" : "https://github.com/dice-group/rtaso/main/rtaso.owl#Accident",
    "baseIri" : "https://github.com/dice-group/rtaso/main/rtaso.owl",
    "instances" : 0,
    "label" : {
      "IRI-based" : "Accident",
      "undefined" : "Accident"
    },
    "comment" : {
      "undefined" : "Represents an accident event."
    },
    "attributes" : [ "external" ],
    "id" : "1",
    "superClasses" : [ "27" ]
  }, {
    "iri" : "http://www.w3.org/2001/XMLSchema#string",
    "baseIri" : "http://www.w3.org/2001/XMLSchema",
    "id" : "22",
    "label" : {
      "IRI-based" : "string"
    }
  }, {
    "iri" : "http://xmlns.com/foaf/0.1/Person",
    "baseIri" : "http://xmlns.com/foaf/0.1",
    "instances" : 0,
    "label" : {
      "IRI-based" : "Person"
    },
    "subClasses" : [ "18", "4" ],
    "attributes" : [ "external" ],
    "id" : "31"
  }, {
    "iri" : "http://www.w3.org/2001/XMLSchema#string",
    "baseIri" : "http://www.w3.org/2001/XMLSchema",
    "id" : "39",
    "label" : {
      "IRI-based" : "string"
    }
  }, {
    "iri" : "http://www.w3.org/2001/XMLSchema#string",
    "baseIri" : "http://www.w3.org/2001/XMLSchema",
    "id" : "41",
    "label" : {
      "IRI-based" : "string"
    }
  } ],
  "property" : [ {
    "id" : "0",
    "type" : "owl:datatypeProperty"
  }, {
    "id" : "3",
    "type" : "owl:objectProperty"
  }, {
    "id" : "8",
    "type" : "owl:datatypeProperty"
  }, {
    "id" : "17",
    "type" : "owl:datatypeProperty"
  }, {
    "id" : "20",
    "type" : "owl:datatypeProperty"
  }, {
    "id" : "21",
    "type" : "owl:datatypeProperty"
  }, {
    "id" : "25",
    "type" : "owl:datatypeProperty"
  }, {
    "id" : "26",
    "type" : "owl:datatypeProperty"
  }, {
    "id" : "28",
    "type" : "owl:datatypeProperty"
  }, {
    "id" : "29",
    "type" : "owl:datatypeProperty"
  }, {
    "id" : "30",
    "type" : "owl:datatypeProperty"
  }, {
    "id" : "32",
    "type" : "rdfs:SubClassOf"
  }, {
    "id" : "33",
    "type" : "rdfs:SubClassOf"
  }, {
    "id" : "34",
    "type" : "rdfs:SubClassOf"
  }, {
    "id" : "35",
    "type" : "owl:datatypeProperty"
  }, {
    "id" : "36",
    "type" : "rdfs:SubClassOf"
  }, {
    "id" : "37",
    "type" : "rdfs:SubClassOf"
  }, {
    "id" : "38",
    "type" : "owl:datatypeProperty"
  }, {
    "id" : "40",
    "type" : "owl:datatypeProperty"
  }, {
    "id" : "42",
    "type" : "rdfs:SubClassOf"
  } ],
  "propertyAttribute" : [ {
    "iri" : "https://github.com/dice-group/rtaso/main/rtaso.owl#hasCause",
    "baseIri" : "https://github.com/dice-group/rtaso/main/rtaso.owl",
    "range" : "2",
    "label" : {
      "IRI-based" : "hasCause",
      "undefined" : "Cause of Accident"
    },
    "domain" : "1",
    "comment" : {
      "undefined" : "The cause of the accident."
    },
    "attributes" : [ "external", "datatype" ],
    "id" : "0"
  }, {
    "iri" : "https://github.com/dice-group/rtaso/main/rtaso.owl#hasVehicleRelation",
    "baseIri" : "https://github.com/dice-group/rtaso/main/rtaso.owl",
    "range" : "5",
    "label" : {
      "IRI-based" : "hasVehicleRelation",
      "undefined" : "Vehicle Relation"
    },
    "domain" : "4",
    "comment" : {
      "undefined" : "The relationship of the driver to the vehicle."
    },
    "attributes" : [ "external", "object" ],
    "id" : "3"
  }, {
    "iri" : "https://github.com/dice-group/rtaso/main/rtaso.owl#hasDrivingExperience",
    "baseIri" : "https://github.com/dice-group/rtaso/main/rtaso.owl",
    "range" : "9",
    "label" : {
      "IRI-based" : "hasDrivingExperience",
      "undefined" : "Driving Experience"
    },
    "domain" : "4",
    "comment" : {
      "undefined" : "The driving experience of the driver in years."
    },
    "attributes" : [ "external", "datatype" ],
    "id" : "8"
  }, {
    "iri" : "https://github.com/dice-group/rtaso/main/rtaso.owl#hasPedestrianMovement",
    "baseIri" : "https://github.com/dice-group/rtaso/main/rtaso.owl",
    "range" : "14",
    "label" : {
      "IRI-based" : "hasPedestrianMovement",
      "undefined" : "Pedestrian Movement"
    },
    "domain" : "18",
    "comment" : {
      "undefined" : "The movement of the pedestrian during the accident."
    },
    "attributes" : [ "external", "datatype" ],
    "id" : "17"
  }, {
    "iri" : "https://github.com/dice-group/rtaso/main/rtaso.owl#hasEducationLevel",
    "baseIri" : "https://github.com/dice-group/rtaso/main/rtaso.owl",
    "range" : "11",
    "label" : {
      "IRI-based" : "hasEducationLevel",
      "undefined" : "Education Level"
    },
    "domain" : "4",
    "comment" : {
      "undefined" : "The education level of the driver."
    },
    "attributes" : [ "external", "datatype" ],
    "id" : "20"
  }, {
    "iri" : "https://github.com/dice-group/rtaso/main/rtaso.owl#hasType",
    "baseIri" : "https://github.com/dice-group/rtaso/main/rtaso.owl",
    "range" : "22",
    "label" : {
      "IRI-based" : "hasType",
      "undefined" : "Vehicle Type"
    },
    "domain" : "5",
    "comment" : {
      "undefined" : "The type of vehicle involved in the accident."
    },
    "attributes" : [ "external", "datatype" ],
    "id" : "21"
  }, {
    "iri" : "https://github.com/dice-group/rtaso/main/rtaso.owl#hasGender",
    "baseIri" : "https://github.com/dice-group/rtaso/main/rtaso.owl",
    "range" : "12",
    "label" : {
      "IRI-based" : "hasGender",
      "undefined" : "Driver Gender"
    },
    "domain" : "4",
    "comment" : {
      "undefined" : "The gender of the driver."
    },
    "attributes" : [ "external", "datatype" ],
    "id" : "25"
  }, {
    "iri" : "https://github.com/dice-group/rtaso/main/rtaso.owl#hasCollisionType",
    "baseIri" : "https://github.com/dice-group/rtaso/main/rtaso.owl",
    "range" : "10",
    "label" : {
      "IRI-based" : "hasCollisionType",
      "undefined" : "Collision Type"
    },
    "domain" : "1",
    "comment" : {
      "undefined" : "The type of collision during the accident."
    },
    "attributes" : [ "external", "datatype" ],
    "id" : "26"
  }, {
    "iri" : "https://github.com/dice-group/rtaso/main/rtaso.owl#hasAge",
    "baseIri" : "https://github.com/dice-group/rtaso/main/rtaso.owl",
    "range" : "24",
    "label" : {
      "IRI-based" : "hasAge",
      "undefined" : "Driver Age"
    },
    "domain" : "4",
    "comment" : {
      "undefined" : "The age of the driver."
    },
    "attributes" : [ "external", "datatype" ],
    "id" : "28"
  }, {
    "iri" : "https://github.com/dice-group/rtaso/main/rtaso.owl#hasSeverity",
    "baseIri" : "https://github.com/dice-group/rtaso/main/rtaso.owl",
    "range" : "16",
    "label" : {
      "IRI-based" : "hasSeverity",
      "undefined" : "Accident Severity"
    },
    "domain" : "1",
    "comment" : {
      "undefined" : "The severity of the accident."
    },
    "attributes" : [ "external", "datatype" ],
    "id" : "29"
  }, {
    "iri" : "https://github.com/dice-group/rtaso/main/rtaso.owl#hasLightCondition",
    "baseIri" : "https://github.com/dice-group/rtaso/main/rtaso.owl",
    "range" : "13",
    "label" : {
      "IRI-based" : "hasLightCondition",
      "undefined" : "Light Condition"
    },
    "domain" : "23",
    "comment" : {
      "undefined" : "The light condition during the accident."
    },
    "attributes" : [ "external", "datatype" ],
    "id" : "30"
  }, {
    "range" : "31",
    "domain" : "4",
    "attributes" : [ "anonymous", "object" ],
    "id" : "32"
  }, {
    "range" : "31",
    "domain" : "18",
    "attributes" : [ "anonymous", "object" ],
    "id" : "33"
  }, {
    "range" : "27",
    "domain" : "1",
    "attributes" : [ "anonymous", "object" ],
    "id" : "34"
  }, {
    "iri" : "https://github.com/dice-group/rtaso/main/rtaso.owl#hasServiceLife",
    "baseIri" : "https://github.com/dice-group/rtaso/main/rtaso.owl",
    "range" : "15",
    "label" : {
      "IRI-based" : "hasServiceLife",
      "undefined" : "Service Life"
    },
    "domain" : "5",
    "comment" : {
      "undefined" : "The service life of the vehicle in years."
    },
    "attributes" : [ "external", "datatype" ],
    "id" : "35"
  }, {
    "range" : "19",
    "domain" : "5",
    "attributes" : [ "anonymous", "object" ],
    "id" : "36"
  }, {
    "range" : "7",
    "domain" : "23",
    "attributes" : [ "anonymous", "object" ],
    "id" : "37"
  }, {
    "iri" : "https://github.com/dice-group/rtaso/main/rtaso.owl#hasWeatherCondition",
    "baseIri" : "https://github.com/dice-group/rtaso/main/rtaso.owl",
    "range" : "39",
    "label" : {
      "IRI-based" : "hasWeatherCondition",
      "undefined" : "Weather Condition"
    },
    "domain" : "23",
    "comment" : {
      "undefined" : "The weather condition during the accident."
    },
    "attributes" : [ "external", "datatype" ],
    "id" : "38"
  }, {
    "iri" : "https://github.com/dice-group/rtaso/main/rtaso.owl#hasVehicleMovement",
    "baseIri" : "https://github.com/dice-group/rtaso/main/rtaso.owl",
    "range" : "41",
    "label" : {
      "IRI-based" : "hasVehicleMovement",
      "undefined" : "Vehicle Movement"
    },
    "domain" : "1",
    "comment" : {
      "undefined" : "The movement of the vehicle during the accident."
    },
    "attributes" : [ "external", "datatype" ],
    "id" : "40"
  }, {
    "range" : "7",
    "domain" : "6",
    "attributes" : [ "anonymous", "object" ],
    "id" : "42"
  } ]
}